MANIFEST.in
README.rst
setup.py
4ch.egg-info/PKG-INFO
4ch.egg-info/SOURCES.txt
4ch.egg-info/dependency_links.txt
4ch.egg-info/not-zip-safe
4ch.egg-info/requires.txt
4ch.egg-info/top_level.txt
fourch/__init__.py
fourch/_version.py
fourch/board.py
fourch/boards.py
fourch/fourch.py
fourch/reply.py
fourch/thread.py