Metadata-Version: 1.1
Name: 4ch
Version: 0.4.0
Summary: Python wrapper for the 4chan JSON API.
Home-page: https://github.com/plausibility/4ch
Author: plausibility
Author-email: chris@gibsonsec.org
License: MIT
Keywords: wrapper 4chan chan json
Platform: UNKNOWN
Classifier: Development Status :: 1 - Planning
Classifier: Intended Audience :: Developers
Classifier: License :: OSI Approved :: MIT License
Classifier: Operating System :: OS Independent
Classifier: Programming Language :: Python :: 2
